hellopi.py
ipxray/__init__.py
ipxray/packet.py
hellopi-1.0.dist-info/LICENSE
hellopi-1.0.dist-info/METADATA
hellopi-1.0.dist-info/WHEEL
hellopi-1.0.dist-info/entry_points.txt
hellopi-1.0.dist-info/top_level.txt
hellopi-1.0.dist-info/RECORD
