Metadata-Version: 2.1
Name: hellopi
Version: 1.0
Summary: A program to identify the ip address of Raspberry Pis (or other devices) added to the local area network.
Home-page: https://github.com/300bps/hellopi
Author: David Smith
Author-email: x300bps@icloud.com
License: MIT
Keywords: raspberry pi,networking,dhcp,ip,ip address,discovery,device discovery,device,linux,windows
Platform: UNKNOWN
Classifier: Programming Language :: Python :: 3
Classifier: License :: OSI Approved :: MIT License
Classifier: Operating System :: POSIX :: BSD
Classifier: Operating System :: POSIX :: Linux
Classifier: Operating System :: MacOS :: MacOS X
Classifier: Operating System :: Microsoft :: Windows
Classifier: Topic :: System :: Hardware
Classifier: Topic :: System :: Networking
Classifier: Topic :: System :: Networking :: Monitoring
